fengxi_mcp_demo/__init__.py
fengxi_mcp_demo-0.1.1.dist-info/WHEEL
fengxi_mcp_demo-0.1.1.dist-info/entry_points.txt
fengxi_mcp_demo-0.1.1.dist-info/METADATA
fengxi_mcp_demo-0.1.1.dist-info/RECORD
