Metadata-Version: 2.3
Name: fengxi-mcp-demo
Version: 0.1.1
Summary: Add your description here
Author-email: 601125648@qq.com
Requires-Dist: mcp[cli]>=1.16.0
Requires-Python: >=3.13
